datavalidation/__init__.py
datavalidation/apps.py
datavalidation/config.py
datavalidation/constants.py
datavalidation/logging.py
datavalidation/models.py
datavalidation/registry.py
datavalidation/results.py
datavalidation/runners.py
datavalidation/serializers.py
datavalidation/types.py
datavalidation/utils.py
datavalidation/views.py
datavalidation/viewsets.py
datavalidation/admin/__init__.py
datavalidation/admin/main.py
datavalidation/admin/mixins.py
datavalidation/management/__init__.py
datavalidation/management/commands/__init__.py
datavalidation/management/commands/validate.py
datavalidation/migrations/0001_initial.py
datavalidation/migrations/0002_validator_execution_time.py
datavalidation/migrations/0003_remove_validator_is_class_method.py
datavalidation/migrations/0004_auto_20200724_1816.py
datavalidation/migrations/__init__.py
datavalidation/static/datavalidation/admin/asset-manifest.json
datavalidation/static/datavalidation/admin/favicon.ico
datavalidation/static/datavalidation/admin/manifest.json
datavalidation/static/datavalidation/admin/precache-manifest.f3334b545e17c08fc7f7d755078ba684.js
datavalidation/static/datavalidation/admin/robots.txt
datavalidation/static/datavalidation/admin/service-worker.js
datavalidation/static/datavalidation/admin/static/css/2.chunk.css
datavalidation/static/datavalidation/admin/static/css/2.chunk.css.map
datavalidation/static/datavalidation/admin/static/css/main.chunk.css
datavalidation/static/datavalidation/admin/static/css/main.chunk.css.map
datavalidation/static/datavalidation/admin/static/js/2.chunk.js
datavalidation/static/datavalidation/admin/static/js/2.chunk.js.LICENSE.txt
datavalidation/static/datavalidation/admin/static/js/2.chunk.js.map
datavalidation/static/datavalidation/admin/static/js/main.chunk.js
datavalidation/static/datavalidation/admin/static/js/main.chunk.js.map
datavalidation/static/datavalidation/admin/static/js/runtime-main.js
datavalidation/static/datavalidation/admin/static/js/runtime-main.js.map
django_data_validation-0.0.1.dist-info/LICENSE
django_data_validation-0.0.1.dist-info/METADATA
django_data_validation-0.0.1.dist-info/WHEEL
django_data_validation-0.0.1.dist-info/top_level.txt
django_data_validation-0.0.1.dist-info/RECORD
