Metadata-Version: 2.1
Name: django-data-validation
Version: 0.0.1
Summary: A Django app to manage the validation of your data.
Home-page: https://github.com/VersBersh/django-data-validation
Author: Oliver Chambers
Author-email: django.data.validation@gmail.com
License: MIT
Platform: UNKNOWN
Classifier: License :: OSI Approved :: MIT License
Classifier: Programming Language :: Python
Classifier: Programming Language :: Python :: 3
Classifier: Programming Language :: Python :: 3.6
Classifier: Programming Language :: Python :: Implementation :: CPython
Classifier: Framework :: Django :: 2.0
Requires-Python: ~=3.6.0
Requires-Dist: django (>=2.2)
Requires-Dist: django-enumfields (>=2.0.0)
Requires-Dist: djangorestframework (>=3.1)
Requires-Dist: termcolor
Requires-Dist: tqdm
Requires-Dist: dataclasses ; python_version < "3.7"
